{
  "context": "vessels.self",
  "updates": [
    {
      "timestamp": "2026-03-21T05:33:18.249000+00:00",
      "values": [
        {
          "path": "navigation.position",
          "value": {
            "latitude": 37.8972963,
            "longitude": -122.4564408
          }
        },
        {
          "path": "navigation.racing.timeToStart",
          "value": 300.0
        },
        {
          "path": "navigation.racing.startLinePort",
          "value": {
            "latitude": 37.781062162734244,
            "longitude": -122.3854897129328
          }
        },
        {
          "path": "navigation.racing.startLineStb",
          "value": {
            "latitude": 37.78107349606757,
            "longitude": -122.38551557959867
          }
        },
        {
          "path": "navigation.racing.startLineLength",
          "value": 2.6
        },
        {
          "path": "navigation.racing.distanceStartline",
          "value": 14130.3
        },
        {
          "path": "navigation.racing.timeToLine",
          "value": 2179880.8171400167
        },
        {
          "path": "navigation.attitude.pitch",
          "value": 0.0091
        },
        {
          "path": "navigation.attitude.roll",
          "value": -0.0236
        },
        {
          "path": "navigation.rateOfTurn",
          "value": 0.00019172
        },
        {
          "path": "navigation.trip.log",
          "value": 159152.0
        },
        {
          "path": "navigation.log",
          "value": 159152.0
        },
        {
          "path": "navigation.headingMagnetic",
          "value": 1.6609
        },
        {
          "path": "navigation.speedOverGround",
          "value": 0.05
        },
        {
          "path": "navigation.speedThroughWater",
          "value": 0.0
        },
        {
          "path": "navigation.gnss.antennaAltitude",
          "value": -2.5
        },
        {
          "path": "navigation.gnss.satellites",
          "value": 8.0
        },
        {
          "path": "navigation.gnss.horizontalDilution",
          "value": 1.18
        },
        {
          "path": "navigation.gnss.geoidalSeparation",
          "value": -29.6
        },
        {
          "path": "navigation.gnss.differentialAge",
          "value": 0.0
        },
        {
          "path": "navigation.gnss.differentialReference",
          "value": 0.0
        },
        {
          "path": "navigation.gnss.satellitesInView.count",
          "value": 13.0
        },
        {
          "path": "navigation.courseOverGroundTrue",
          "value": 0.3491
        },
        {
          "path": "navigation.magneticVariation",
          "value": 0.2305
        },
        {
          "path": "environment.wind.speedTrue",
          "value": 0.65
        },
        {
          "path": "environment.wind.angleTrueWater",
          "value": 1.4374
        },
        {
          "path": "environment.wind.speedApparent",
          "value": 0.49
        },
        {
          "path": "environment.wind.angleApparent",
          "value": 1.5929
        },
        {
          "path": "environment.wind.directionMagnetic",
          "value": 2.4707
        },
        {
          "path": "environment.wind.angleTrueWaterDamped",
          "value": 1.445
        },
        {
          "path": "environment.rpi.gpu.temperature",
          "value": 330.25
        },
        {
          "path": "environment.rpi.cpu.temperature",
          "value": 329.35
        },
        {
          "path": "environment.rpi.cpu.utilisation",
          "value": 0.16
        },
        {
          "path": "environment.rpi.cpu.core.1.utilisation",
          "value": 0.17
        },
        {
          "path": "environment.rpi.cpu.core.2.utilisation",
          "value": 0.14
        },
        {
          "path": "environment.rpi.cpu.core.3.utilisation",
          "value": 0.21
        },
        {
          "path": "environment.rpi.cpu.core.4.utilisation",
          "value": 0.13
        },
        {
          "path": "environment.rpi.memory.utilisation",
          "value": 0.13
        },
        {
          "path": "environment.rpi.sd.utilisation",
          "value": 0.37
        },
        {
          "path": "environment.depth.belowTransducer",
          "value": 3.99
        },
        {
          "path": "environment.water.temperature",
          "value": 290.928
        },
        {
          "path": "environment.tide.heightNow",
          "value": 1.023
        },
        {
          "path": "environment.tide.heightHigh",
          "value": 1.806
        },
        {
          "path": "environment.tide.heightLow",
          "value": -0.083
        },
        {
          "path": "environment.inside.refridgerator.temperature",
          "value": 277.65
        },
        {
          "path": "environment.inside.temperature",
          "value": 296.9625
        },
        {
          "path": "environment.inside.freezer.temperature",
          "value": 271.5875
        },
        {
          "path": "environment.outside.temperature",
          "value": 289.65
        },
        {
          "path": "propulsion.port.revolutions",
          "value": 0.0
        },
        {
          "path": "propulsion.port.drive.trimState",
          "value": -1.0
        },
        {
          "path": "tanks.fuel.0.currentVolume",
          "value": 0.08456000000000001
        },
        {
          "path": "tanks.fuel.0.currentLevel",
          "value": 0.56
        },
        {
          "path": "tanks.fuel.0.capacity",
          "value": 0.151
        },
        {
          "path": "tanks.fuel.reserve.temperature",
          "value": 292.15
        },
        {
          "path": "tanks.fuel.reserve.capacity",
          "value": 0.151
        },
        {
          "path": "tanks.fuel.reserve.currentVolume",
          "value": 0.12466309243777517
        },
        {
          "path": "tanks.fuel.reserve.currentLevel",
          "value": 0.8255833936276501
        },
        {
          "path": "tanks.freshWater.0.currentVolume",
          "value": 0.2014
        },
        {
          "path": "tanks.freshWater.0.currentLevel",
          "value": 0.7599999999999999
        },
        {
          "path": "tanks.freshWater.0.capacity",
          "value": 0.265
        },
        {
          "path": "tanks.freshWater.1.currentVolume",
          "value": 0.19079999999999997
        },
        {
          "path": "tanks.freshWater.1.currentLevel",
          "value": 0.7199999999999999
        },
        {
          "path": "tanks.freshWater.1.capacity",
          "value": 0.265
        },
        {
          "path": "tanks.liveWell.0.currentLevel",
          "value": 0.06666666666666657
        },
        {
          "path": "tanks.liveWell.0.capacity",
          "value": 214748.36469999998
        },
        {
          "path": "tanks.propane.a.temperature",
          "value": 294.15
        },
        {
          "path": "tanks.propane.a.currentLevel",
          "value": 0.4075377573913045
        },
        {
          "path": "tanks.propane.b.temperature",
          "value": 292.15
        },
        {
          "path": "tanks.propane.b.currentLevel",
          "value": 0.8319240234782611
        },
        {
          "path": "tanks.blackwater.bow.temperature",
          "value": 294.15
        },
        {
          "path": "tanks.blackwater.bow.currentLevel",
          "value": 0.0
        },
        {
          "path": "electrical.batteries.house.capacity.dischargeSinceFull",
          "value": -101160.0
        },
        {
          "path": "electrical.batteries.house.capacity.stateOfCharge",
          "value": 0.934
        },
        {
          "path": "electrical.batteries.house.capacity.timeRemaining",
          "value": 250740.0
        },
        {
          "path": "electrical.batteries.house.current",
          "value": -3.307
        },
        {
          "path": "electrical.batteries.house.power",
          "value": -41.63513
        },
        {
          "path": "electrical.batteries.house.voltage",
          "value": 12.59
        },
        {
          "path": "internet.ping.jitter",
          "value": 3.904
        },
        {
          "path": "internet.ping.latency",
          "value": 39.523
        },
        {
          "path": "internet.packetLoss",
          "value": 0.0
        },
        {
          "path": "internet.speed.download",
          "value": 19.1063
        },
        {
          "path": "internet.speed.upload",
          "value": 18.0718625
        }
      ]
    }
  ]
}