{
  "timestamp": "2026-02-05T09:22:23.093000+00:00",
  "file": "2026-02-05T09-22-23.093000Z.json",
  "numericValues": {
    "design.draft.maximum": 2.31,
    "design.length.overall": 12.95,
    "design.beam": 4.11,
    "design.airHeight": 18.0,
    "design.aisShipType.id": 36.0,
    "sensors.gps.fromBow": 7.95,
    "sensors.gps.fromCenter": 0.45,
    "sensors.fuel.reserve-D3-D4-D2-7D-A9-EC.RSSI": -69.0,
    "sensors.fuel.reserve-D3-D4-D2-7D-A9-EC.battery.voltage": 2.96875,
    "sensors.fuel.reserve-D3-D4-D2-7D-A9-EC.battery.strength": 1.0,
    "sensors.fuel.reserve-D3-D4-D2-7D-A9-EC.readingQuality": 3.0,
    "sensors.propane.a-E9-5D-A9-2D-FD-A5.RSSI": -76.0,
    "sensors.propane.a-E9-5D-A9-2D-FD-A5.battery.voltage": 2.96875,
    "sensors.propane.a-E9-5D-A9-2D-FD-A5.battery.strength": 1.0,
    "sensors.propane.a-E9-5D-A9-2D-FD-A5.readingQuality": 3.0,
    "sensors.propane.b-CD-A5-8E-1A-0E-FC.RSSI": -73.0,
    "sensors.propane.b-CD-A5-8E-1A-0E-FC.battery.voltage": 2.9375,
    "sensors.propane.b-CD-A5-8E-1A-0E-FC.battery.strength": 1.0,
    "sensors.propane.b-CD-A5-8E-1A-0E-FC.readingQuality": 3.0,
    "sensors.blackwater.bow-D3-8C-0D-58-BA-27.RSSI": -70.0,
    "sensors.blackwater.bow-D3-8C-0D-58-BA-27.battery.voltage": 2.90625,
    "sensors.blackwater.bow-D3-8C-0D-58-BA-27.battery.strength": 1.0,
    "sensors.blackwater.bow-D3-8C-0D-58-BA-27.readingQuality": 0.0,
    "sensors.ais.boundingBox.latmin": 37.736453462179405,
    "sensors.ais.boundingBox.latmax": 37.82599623362132,
    "sensors.ais.boundingBox.lonmin": -122.4411264261,
    "sensors.ais.boundingBox.lonmax": -122.3286896890513,
    "entertainment.device.fusion1.outputAlarms": 0.0,
    "environment.rpi.gpu.temperature": 328.05,
    "environment.rpi.cpu.temperature": 329.35,
    "environment.rpi.cpu.utilisation": 0.31,
    "environment.rpi.cpu.core.1.utilisation": 0.28,
    "environment.rpi.cpu.core.2.utilisation": 0.35,
    "environment.rpi.cpu.core.3.utilisation": 0.33,
    "environment.rpi.cpu.core.4.utilisation": 0.25,
    "environment.rpi.memory.utilisation": 0.34,
    "environment.rpi.sd.utilisation": 0.39,
    "environment.inside.temperature": 290.8256839811802,
    "environment.inside.humidity": 0.6240487489700189,
    "environment.inside.pressure": 102097.31681160521,
    "environment.inside.airQuality.tvoc": 211.0,
    "environment.inside.airQuality.eco2": 439.0,
    "environment.inside.refridgerator.temperature": 277.65,
    "environment.inside.freezer.temperature": 264.775,
    "environment.outside.temperature": 285.65,
    "environment.outside.nws.alertCount": 4.0,
    "environment.tide.heightNow": 1.783,
    "environment.tide.heightHigh": 1.876,
    "environment.tide.heightLow": 0.489,
    "navigation.magneticVariation": 0.2249503163015448,
    "navigation.position.latitude": 37.7810045,
    "navigation.position.longitude": -122.3854825,
    "navigation.speedOverGround": 0.05305555555555556,
    "navigation.magneticVariationAgeOfService": 1770283343.0,
    "navigation.gnss.satellites": 6.0,
    "navigation.gnss.antennaAltitude": 2.9,
    "navigation.gnss.horizontalDilution": 1.89,
    "navigation.gnss.geoidalSeparation": -29.7,
    "navigation.gnss.differentialAge": 0.0,
    "navigation.gnss.differentialReference": 0.0,
    "navigation.gnss.satellitesInView.count": 14.0,
    "navigation.headingTrue": 0.9892439794059449,
    "navigation.headingMagnetic": 0.7642936631044001,
    "navigation.attitude.roll": -0.0018448130701000003,
    "navigation.attitude.pitch": -0.004738569049500001,
    "navigation.attitude.yaw": 0.7642936631044001,
    "electrical.batteries.house.capacity.dischargeSinceFull": -360.0,
    "electrical.batteries.house.capacity.stateOfCharge": 1.0,
    "electrical.batteries.house.capacity.timeRemaining": 864000.0,
    "electrical.batteries.house.current": 0.0,
    "electrical.batteries.house.power": 0.0,
    "electrical.batteries.house.voltage": 13.13,
    "tanks.fuel.reserve.temperature": 288.15,
    "tanks.fuel.reserve.capacity": 0.151,
    "tanks.fuel.reserve.currentVolume": 0.030613402232888588,
    "tanks.fuel.reserve.currentLevel": 0.20273776313171255,
    "tanks.propane.a.temperature": 288.15,
    "tanks.propane.a.currentLevel": 0.4012176208695653,
    "tanks.propane.b.temperature": 285.15,
    "tanks.propane.b.currentLevel": 0.8724534710869567,
    "tanks.blackwater.bow.temperature": 287.15,
    "tanks.blackwater.bow.currentLevel": 0.0,
    "internet.ping.jitter": 2.236,
    "internet.ping.latency": 71.97,
    "internet.speed.download": 19.4751375,
    "internet.speed.upload": 17.3141125,
    "internet.packetLoss": 1.0033444816053512
  },
  "speedOverGround": 0.05305555555555556,
  "courseOverGroundTrue": 0.9892439794059449
}