{
  "context": "vessels.self",
  "updates": [
    {
      "timestamp": "2026-07-11T22:44:12.824000+00:00",
      "values": [
        {
          "path": "navigation.position",
          "value": {
            "latitude": 37.8248387,
            "longitude": -122.5609497
          }
        },
        {
          "path": "environment.rpi.gpu.temperature",
          "value": 330.25
        },
        {
          "path": "environment.rpi.cpu.temperature",
          "value": 329.9
        },
        {
          "path": "environment.rpi.cpu.utilisation",
          "value": 0.31
        },
        {
          "path": "environment.rpi.cpu.core.1.utilisation",
          "value": 0.2
        },
        {
          "path": "environment.rpi.cpu.core.2.utilisation",
          "value": 0.25
        },
        {
          "path": "environment.rpi.cpu.core.3.utilisation",
          "value": 0.43
        },
        {
          "path": "environment.rpi.cpu.core.4.utilisation",
          "value": 0.36
        },
        {
          "path": "environment.rpi.memory.utilisation",
          "value": 0.29
        },
        {
          "path": "environment.rpi.sd.utilisation",
          "value": 0.43
        },
        {
          "path": "environment.depth.belowTransducer",
          "value": 8.96
        },
        {
          "path": "environment.wind.directionMagnetic",
          "value": 4.647214692820413
        },
        {
          "path": "environment.wind.speedApparent",
          "value": 9.26
        },
        {
          "path": "environment.wind.angleApparent",
          "value": -0.267285307179586
        },
        {
          "path": "environment.wind.speedOverGround",
          "value": 7.115
        },
        {
          "path": "environment.wind.directionTrue",
          "value": 4.424838576406357
        },
        {
          "path": "environment.wind.speedTrue",
          "value": 8.81
        },
        {
          "path": "environment.wind.angleTrueWater",
          "value": 6.0638
        },
        {
          "path": "environment.wind.angleTrueWaterDamped",
          "value": -2.811
        },
        {
          "path": "environment.wind.oneMinute.gustTrue",
          "value": 8.99
        },
        {
          "path": "environment.wind.fiveMinutes.gustTrue",
          "value": 9.32
        },
        {
          "path": "environment.wind.oneHour.gustTrue",
          "value": 15.08
        },
        {
          "path": "environment.current",
          "value": {
            "drift": 0.08333333333333333,
            "setTrue": 0.7853981633974483
          }
        },
        {
          "path": "environment.current.drift",
          "value": 0.4558835332660653
        },
        {
          "path": "environment.current.setTrue",
          "value": 2.5995257649243513
        },
        {
          "path": "environment.current.setMagnetic",
          "value": 2.364225764924351
        },
        {
          "path": "environment.current.driftImpact",
          "value": -0.36036279946968025
        },
        {
          "path": "environment.water.temperature",
          "value": 289.799
        },
        {
          "path": "environment.water.waves.significantHeight",
          "value": 1.12
        },
        {
          "path": "environment.water.waves.period",
          "value": 8.05
        },
        {
          "path": "environment.water.waves.direction",
          "value": 4.6600291028248595
        },
        {
          "path": "environment.water.waves.windWaveHeight",
          "value": 0.4
        },
        {
          "path": "environment.water.swell.height",
          "value": 0.88
        },
        {
          "path": "environment.water.swell.period",
          "value": 5.05
        },
        {
          "path": "environment.water.swell.direction",
          "value": 5.131268000863329
        },
        {
          "path": "environment.currentImpact",
          "value": -0.37
        },
        {
          "path": "environment.tide.heightNow",
          "value": 1.049658239359756
        },
        {
          "path": "environment.tide.timeToNextExtreme",
          "value": 18672.0
        },
        {
          "path": "environment.tide.heightLow",
          "value": -0.37719942811461427
        },
        {
          "path": "environment.tide.heightHigh",
          "value": 2.2036816717679413
        },
        {
          "path": "environment.outside.temperature",
          "value": 291.65
        },
        {
          "path": "environment.outside.pressure",
          "value": 101320.0
        },
        {
          "path": "environment.outside.relativeHumidity",
          "value": 0.856
        },
        {
          "path": "environment.outside.dewPointTemperature",
          "value": 285.65
        },
        {
          "path": "environment.outside.theoreticalWindChillTemperature",
          "value": 290.04999999999995
        },
        {
          "path": "environment.outside.apparentWindChillTemperature",
          "value": 290.04999999999995
        },
        {
          "path": "environment.outside.heatIndexTemperature",
          "value": 290.04999999999995
        },
        {
          "path": "environment.outside.airDensity",
          "value": 1.2094265890734321
        },
        {
          "path": "environment.weather.wetBulbGlobeTemperature",
          "value": 292.58228588095284
        },
        {
          "path": "environment.weather.apparentTemperature",
          "value": 288.15
        },
        {
          "path": "environment.weather.absoluteHumidity",
          "value": 0.012283195571115598
        },
        {
          "path": "environment.weather.speedGust",
          "value": 8.2
        },
        {
          "path": "environment.weather.gustFactor",
          "value": 1.1524947294448347
        },
        {
          "path": "environment.weather.beaufortScale",
          "value": 4.0
        },
        {
          "path": "environment.weather.windSpeedApparent",
          "value": 11.598050377632832
        },
        {
          "path": "environment.weather.windAngleApparent",
          "value": -0.043570813126142305
        },
        {
          "path": "environment.weather.uvIndex",
          "value": 6.825
        },
        {
          "path": "environment.weather.visibility",
          "value": 13800.0
        },
        {
          "path": "environment.weather.cloudCover",
          "value": 1.0
        },
        {
          "path": "environment.weather.precipitationLastHour",
          "value": 0.0
        },
        {
          "path": "environment.weather.heatStressIndex",
          "value": 0.0
        },
        {
          "path": "environment.inside.refridgerator.temperature",
          "value": 283.15
        },
        {
          "path": "environment.inside.temperature",
          "value": 297.2125
        },
        {
          "path": "environment.inside.freezer.temperature",
          "value": 282.65
        },
        {
          "path": "electrical.batteries.house.capacity.dischargeSinceFull",
          "value": 0.0
        },
        {
          "path": "electrical.batteries.house.capacity.stateOfCharge",
          "value": 1.0
        },
        {
          "path": "electrical.batteries.house.capacity.timeRemaining",
          "value": 864000.0
        },
        {
          "path": "electrical.batteries.house.current",
          "value": 3.955
        },
        {
          "path": "electrical.batteries.house.power",
          "value": 53.1552
        },
        {
          "path": "electrical.batteries.house.voltage",
          "value": 13.44
        },
        {
          "path": "electrical.solar.bimini.current",
          "value": 0.9
        },
        {
          "path": "electrical.solar.bimini.loadCurrent",
          "value": 0.0
        },
        {
          "path": "electrical.solar.bimini.panelPower",
          "value": 14.0
        },
        {
          "path": "electrical.solar.bimini.voltage",
          "value": 13.68
        },
        {
          "path": "electrical.solar.bimini.yieldToday",
          "value": 252000.0
        },
        {
          "path": "navigation.headingMagnetic",
          "value": 4.9132
        },
        {
          "path": "navigation.trip.log",
          "value": 1018879.0
        },
        {
          "path": "navigation.log",
          "value": 1018879.0
        },
        {
          "path": "navigation.speedOverGround",
          "value": 3.71
        },
        {
          "path": "navigation.courseOverGroundTrue",
          "value": 5.221
        },
        {
          "path": "navigation.attitude.pitch",
          "value": 0.0164
        },
        {
          "path": "navigation.attitude.roll",
          "value": 0.0322
        },
        {
          "path": "navigation.rateOfTurn",
          "value": -0.01514794
        },
        {
          "path": "navigation.speedThroughWater",
          "value": 4.05
        },
        {
          "path": "navigation.gnss.antennaAltitude",
          "value": -28.672185
        },
        {
          "path": "navigation.gnss.satellites",
          "value": 11.0
        },
        {
          "path": "navigation.gnss.horizontalDilution",
          "value": 0.77
        },
        {
          "path": "navigation.gnss.geoidalSeparation",
          "value": -32.15
        },
        {
          "path": "navigation.gnss.positionDilution",
          "value": 1.17
        },
        {
          "path": "navigation.gnss.satellitesInView.count",
          "value": 11.0
        },
        {
          "path": "navigation.gnss.differentialAge",
          "value": 0.0
        },
        {
          "path": "navigation.gnss.differentialReference",
          "value": 0.0
        },
        {
          "path": "navigation.magneticVariation",
          "value": 0.2353
        },
        {
          "path": "navigation.averageSpeedThroughWater",
          "value": 4.17
        },
        {
          "path": "navigation.averageSpeedOverGround",
          "value": 3.8
        },
        {
          "path": "navigation.courseRhumbline.nextPoint.bearingTrue",
          "value": 5.160938599325627
        },
        {
          "path": "navigation.courseRhumbline.nextPoint.velocityMadeGood",
          "value": 3.390704192311729
        },
        {
          "path": "navigation.courseRhumbline.nextPoint.distance",
          "value": 13539.972011427735
        },
        {
          "path": "navigation.courseRhumbline.nextPoint.arrivalCircle",
          "value": 0.0
        },
        {
          "path": "navigation.courseRhumbline.crossTrackError",
          "value": 0.0
        },
        {
          "path": "navigation.courseRhumbline.bearingTrackTrue",
          "value": 5.160938599325627
        },
        {
          "path": "navigation.courseRhumbline.bearingOriginToDestinationTrue",
          "value": 5.160938599325627
        },
        {
          "path": "navigation.courseRhumbline.bearingToDestinationTrue",
          "value": 5.160938599325627
        },
        {
          "path": "navigation.courseGreatCircle.nextPoint.arrivalCircle",
          "value": 0.0
        },
        {
          "path": "propulsion.port.revolutions",
          "value": 48.928958333333334
        },
        {
          "path": "propulsion.port.drive.trimState",
          "value": -1.0
        },
        {
          "path": "propulsion.port.runTime",
          "value": 5918.135000000002
        },
        {
          "path": "propulsion.port.runTimeTrip",
          "value": 5918.135000000002
        },
        {
          "path": "tanks.fuel.0.currentVolume",
          "value": 0.036239999999999994
        },
        {
          "path": "tanks.fuel.0.currentLevel",
          "value": 0.24
        },
        {
          "path": "tanks.fuel.0.capacity",
          "value": 0.151
        },
        {
          "path": "tanks.fuel.reserve.temperature",
          "value": 291.15
        },
        {
          "path": "tanks.fuel.reserve.capacity",
          "value": 0.11356229999999999
        },
        {
          "path": "tanks.fuel.reserve.currentVolume",
          "value": 0.08486152118983854
        },
        {
          "path": "tanks.fuel.reserve.currentLevel",
          "value": 0.7472684261400002
        },
        {
          "path": "tanks.freshWater.0.currentVolume",
          "value": 0.265
        },
        {
          "path": "tanks.freshWater.0.currentLevel",
          "value": 1.0
        },
        {
          "path": "tanks.freshWater.0.capacity",
          "value": 0.265
        },
        {
          "path": "tanks.freshWater.1.currentVolume",
          "value": 0.18020000000000003
        },
        {
          "path": "tanks.freshWater.1.currentLevel",
          "value": 0.68
        },
        {
          "path": "tanks.freshWater.1.capacity",
          "value": 0.265
        },
        {
          "path": "tanks.liveWell.0.currentLevel",
          "value": 0.3142857142857142
        },
        {
          "path": "tanks.liveWell.0.capacity",
          "value": 214748.36469999998
        },
        {
          "path": "tanks.propane.a.temperature",
          "value": 293.15
        },
        {
          "path": "tanks.propane.a.currentLevel",
          "value": 0.40166604978260884
        },
        {
          "path": "tanks.propane.b.temperature",
          "value": 290.15
        },
        {
          "path": "tanks.propane.b.currentLevel",
          "value": 0.4405332704347827
        },
        {
          "path": "tanks.blackwater.stern.temperature",
          "value": 291.15
        },
        {
          "path": "tanks.blackwater.stern.currentLevel",
          "value": 0.0
        },
        {
          "path": "internet.ping.jitter",
          "value": 7.767
        },
        {
          "path": "internet.ping.latency",
          "value": 52.173
        },
        {
          "path": "internet.packetLoss",
          "value": 0.0
        },
        {
          "path": "internet.speed.download",
          "value": 4.6477125
        },
        {
          "path": "internet.speed.upload",
          "value": 7.5301875
        }
      ]
    }
  ]
}