{
  "context": "vessels.self",
  "updates": [
    {
      "timestamp": "2026-05-08T20:26:19.049000+00:00",
      "values": [
        {
          "path": "navigation.position",
          "value": {
            "latitude": 37.9799665,
            "longitude": -123.0331145
          }
        },
        {
          "path": "environment.rpi.gpu.temperature",
          "value": 328.55
        },
        {
          "path": "environment.rpi.cpu.temperature",
          "value": 329.9
        },
        {
          "path": "environment.rpi.cpu.utilisation",
          "value": 0.23
        },
        {
          "path": "environment.rpi.cpu.core.1.utilisation",
          "value": 0.22
        },
        {
          "path": "environment.rpi.cpu.core.2.utilisation",
          "value": 0.16
        },
        {
          "path": "environment.rpi.cpu.core.3.utilisation",
          "value": 0.23
        },
        {
          "path": "environment.rpi.cpu.core.4.utilisation",
          "value": 0.31
        },
        {
          "path": "environment.rpi.memory.utilisation",
          "value": 0.15
        },
        {
          "path": "environment.rpi.sd.utilisation",
          "value": 0.38
        },
        {
          "path": "environment.wind.speedTrue",
          "value": 9.469391050906944
        },
        {
          "path": "environment.wind.angleTrueWater",
          "value": -2.335182172773079
        },
        {
          "path": "environment.wind.speedApparent",
          "value": 7.57
        },
        {
          "path": "environment.wind.angleApparent",
          "value": -2.0136853071795864
        },
        {
          "path": "environment.wind.directionMagnetic",
          "value": 5.5179
        },
        {
          "path": "environment.wind.angleTrueWaterDamped",
          "value": -2.217
        },
        {
          "path": "environment.wind.oneMinute.gustTrue",
          "value": 13.913161503095298
        },
        {
          "path": "environment.wind.fiveMinutes.gustTrue",
          "value": 14.807464476586564
        },
        {
          "path": "environment.wind.oneHour.gustTrue",
          "value": 16.166157900570767
        },
        {
          "path": "environment.depth.belowTransducer",
          "value": 44.83
        },
        {
          "path": "environment.water.temperature",
          "value": 285.532
        },
        {
          "path": "environment.currentImpact",
          "value": 0.56
        },
        {
          "path": "environment.outside.temperature",
          "value": 287.65
        },
        {
          "path": "environment.inside.temperature",
          "value": 290.9625
        },
        {
          "path": "environment.inside.freezer.temperature",
          "value": 278.025
        },
        {
          "path": "environment.inside.refridgerator.temperature",
          "value": 281.65
        },
        {
          "path": "environment.tide.heightNow",
          "value": 0.322
        },
        {
          "path": "environment.tide.heightHigh",
          "value": 1.198
        },
        {
          "path": "environment.tide.heightLow",
          "value": 1.007
        },
        {
          "path": "navigation.rateOfTurn",
          "value": 0.04093778
        },
        {
          "path": "navigation.headingMagnetic",
          "value": 1.322
        },
        {
          "path": "navigation.attitude.pitch",
          "value": -0.0103
        },
        {
          "path": "navigation.attitude.roll",
          "value": 0.0822
        },
        {
          "path": "navigation.speedThroughWater",
          "value": 3.3
        },
        {
          "path": "navigation.magneticVariation",
          "value": 0.2324
        },
        {
          "path": "navigation.speedOverGround",
          "value": 4.0
        },
        {
          "path": "navigation.courseOverGroundTrue",
          "value": 1.6182
        },
        {
          "path": "navigation.gnss.antennaAltitude",
          "value": -4.3
        },
        {
          "path": "navigation.gnss.satellites",
          "value": 10.0
        },
        {
          "path": "navigation.gnss.horizontalDilution",
          "value": 0.91
        },
        {
          "path": "navigation.gnss.geoidalSeparation",
          "value": -30.1
        },
        {
          "path": "navigation.gnss.positionDilution",
          "value": 1.41
        },
        {
          "path": "navigation.gnss.satellitesInView.count",
          "value": 11.0
        },
        {
          "path": "navigation.gnss.differentialAge",
          "value": 0.0
        },
        {
          "path": "navigation.gnss.differentialReference",
          "value": 0.0
        },
        {
          "path": "navigation.trip.log",
          "value": 535641.0
        },
        {
          "path": "navigation.log",
          "value": 535641.0
        },
        {
          "path": "navigation.headingTrue",
          "value": 1.5486
        },
        {
          "path": "navigation.averageSpeedThroughWater",
          "value": 3.27
        },
        {
          "path": "navigation.averageSpeedOverGround",
          "value": 3.83
        },
        {
          "path": "navigation.courseRhumbline.nextPoint.position",
          "value": {
            "longitude": -122.99538333333334,
            "latitude": 37.9414
          }
        },
        {
          "path": "navigation.courseRhumbline.nextPoint.bearingTrue",
          "value": 2.484388924318588
        },
        {
          "path": "navigation.courseRhumbline.nextPoint.velocityMadeGood",
          "value": 2.6781984562547203
        },
        {
          "path": "navigation.courseRhumbline.nextPoint.distance",
          "value": 5409.69200456578
        },
        {
          "path": "navigation.courseRhumbline.nextPoint.arrivalCircle",
          "value": 0.0
        },
        {
          "path": "navigation.courseRhumbline.crossTrackError",
          "value": -1876.0760015834078
        },
        {
          "path": "navigation.courseRhumbline.previousPoint.position",
          "value": {
            "latitude": 37.99176416666667,
            "longitude": -123.06956083333333
          }
        },
        {
          "path": "navigation.courseRhumbline.bearingTrackTrue",
          "value": 2.1299998196202217
        },
        {
          "path": "navigation.courseRhumbline.bearingOriginToDestinationTrue",
          "value": 2.1299998196202217
        },
        {
          "path": "navigation.courseRhumbline.bearingToDestinationTrue",
          "value": 2.484388924318588
        },
        {
          "path": "navigation.courseGreatCircle.nextPoint.position",
          "value": {
            "longitude": -122.99538333333334,
            "latitude": 37.9414
          }
        },
        {
          "path": "navigation.courseGreatCircle.nextPoint.arrivalCircle",
          "value": 0.0
        },
        {
          "path": "navigation.courseGreatCircle.previousPoint.position",
          "value": {
            "latitude": 37.99176416666667,
            "longitude": -123.06956083333333
          }
        },
        {
          "path": "navigation.course.calcValues.bearingTrackTrue",
          "value": 2.2813760817874758
        },
        {
          "path": "navigation.course.calcValues.bearingTrackMagnetic",
          "value": 2.513776081787476
        },
        {
          "path": "navigation.course.calcValues.crossTrackError",
          "value": -1089.7430210538644
        },
        {
          "path": "navigation.course.calcValues.previousPoint.distance",
          "value": 3453.040518884609
        },
        {
          "path": "navigation.course.calcValues.distance",
          "value": 5415.944038321955
        },
        {
          "path": "navigation.course.calcValues.bearingTrue",
          "value": 2.4843606956738578
        },
        {
          "path": "navigation.course.calcValues.bearingMagnetic",
          "value": 2.716760695673858
        },
        {
          "path": "navigation.course.calcValues.velocityMadeGood",
          "value": 2.599243615973176
        },
        {
          "path": "navigation.course.calcValues.timeToGo",
          "value": 2083.661
        },
        {
          "path": "propulsion.port.revolutions",
          "value": 0.0
        },
        {
          "path": "propulsion.port.drive.trimState",
          "value": -1.0
        },
        {
          "path": "electrical.batteries.house.capacity.dischargeSinceFull",
          "value": -62639.99999999999
        },
        {
          "path": "electrical.batteries.house.capacity.stateOfCharge",
          "value": 0.958
        },
        {
          "path": "electrical.batteries.house.capacity.timeRemaining",
          "value": 150420.0
        },
        {
          "path": "electrical.batteries.house.current",
          "value": -2.363
        },
        {
          "path": "electrical.batteries.house.power",
          "value": -29.86832
        },
        {
          "path": "electrical.batteries.house.voltage",
          "value": 12.64
        },
        {
          "path": "tanks.fuel.0.currentVolume",
          "value": 0.151
        },
        {
          "path": "tanks.fuel.0.currentLevel",
          "value": 1.0
        },
        {
          "path": "tanks.fuel.0.capacity",
          "value": 0.151
        },
        {
          "path": "tanks.fuel.reserve.temperature",
          "value": 288.15
        },
        {
          "path": "tanks.fuel.reserve.capacity",
          "value": 0.11356229999999999
        },
        {
          "path": "tanks.fuel.reserve.currentVolume",
          "value": 0.08727462252393195
        },
        {
          "path": "tanks.fuel.reserve.currentLevel",
          "value": 0.7685175672202127
        },
        {
          "path": "tanks.freshWater.0.currentVolume",
          "value": 0.265
        },
        {
          "path": "tanks.freshWater.0.currentLevel",
          "value": 1.0
        },
        {
          "path": "tanks.freshWater.0.capacity",
          "value": 0.265
        },
        {
          "path": "tanks.freshWater.1.currentVolume",
          "value": 0.0
        },
        {
          "path": "tanks.freshWater.1.currentLevel",
          "value": 0.0
        },
        {
          "path": "tanks.freshWater.1.capacity",
          "value": 0.265
        },
        {
          "path": "tanks.liveWell.0.currentLevel",
          "value": 0.06666666666666657
        },
        {
          "path": "tanks.liveWell.0.capacity",
          "value": 214748.36469999998
        },
        {
          "path": "tanks.propane.b.temperature",
          "value": 285.15
        },
        {
          "path": "tanks.propane.b.currentLevel",
          "value": 0.563112219130435
        },
        {
          "path": "tanks.propane.a.temperature",
          "value": 288.15
        },
        {
          "path": "tanks.propane.a.currentLevel",
          "value": 0.39577122782608704
        },
        {
          "path": "tanks.blackwater.stern.temperature",
          "value": 288.15
        },
        {
          "path": "tanks.blackwater.stern.currentLevel",
          "value": 0.0
        }
      ]
    }
  ]
}