{
  "context": "vessels.self",
  "updates": [
    {
      "timestamp": "2026-05-09T18:12:25.384000+00:00",
      "values": [
        {
          "path": "navigation.position",
          "value": {
            "latitude": 37.8667135,
            "longitude": -123.0569175
          }
        },
        {
          "path": "environment.rpi.gpu.temperature",
          "value": 331.85
        },
        {
          "path": "environment.rpi.cpu.temperature",
          "value": 329.9
        },
        {
          "path": "environment.rpi.cpu.utilisation",
          "value": 0.48
        },
        {
          "path": "environment.rpi.cpu.core.1.utilisation",
          "value": 0.44
        },
        {
          "path": "environment.rpi.cpu.core.2.utilisation",
          "value": 0.6
        },
        {
          "path": "environment.rpi.cpu.core.3.utilisation",
          "value": 0.35
        },
        {
          "path": "environment.rpi.cpu.core.4.utilisation",
          "value": 0.53
        },
        {
          "path": "environment.rpi.memory.utilisation",
          "value": 0.44
        },
        {
          "path": "environment.rpi.sd.utilisation",
          "value": 0.38
        },
        {
          "path": "environment.wind.speedTrue",
          "value": 11.31
        },
        {
          "path": "environment.wind.angleTrueWater",
          "value": 1.5957
        },
        {
          "path": "environment.wind.speedApparent",
          "value": 13.92
        },
        {
          "path": "environment.wind.angleApparent",
          "value": 1.6357
        },
        {
          "path": "environment.wind.directionMagnetic",
          "value": 5.0322
        },
        {
          "path": "environment.wind.angleTrueWaterDamped",
          "value": 1.829
        },
        {
          "path": "environment.wind.oneMinute.gustTrue",
          "value": 15.307064916612193
        },
        {
          "path": "environment.wind.fiveMinutes.gustTrue",
          "value": 17.874115452118225
        },
        {
          "path": "environment.wind.oneHour.gustTrue",
          "value": 18.47776790247355
        },
        {
          "path": "environment.depth.belowTransducer",
          "value": 88.87
        },
        {
          "path": "environment.water.temperature",
          "value": 285.646
        },
        {
          "path": "environment.currentImpact",
          "value": 0.97
        },
        {
          "path": "environment.outside.temperature",
          "value": 288.15
        },
        {
          "path": "environment.inside.temperature",
          "value": 290.525
        },
        {
          "path": "environment.inside.freezer.temperature",
          "value": 273.4
        },
        {
          "path": "environment.inside.refridgerator.temperature",
          "value": 280.65
        },
        {
          "path": "environment.tide.heightNow",
          "value": 0.062
        },
        {
          "path": "environment.tide.heightHigh",
          "value": 1.269
        },
        {
          "path": "environment.tide.heightLow",
          "value": 0.052
        },
        {
          "path": "navigation.rateOfTurn",
          "value": -0.06950794
        },
        {
          "path": "navigation.headingMagnetic",
          "value": 3.4266
        },
        {
          "path": "navigation.attitude.pitch",
          "value": 0.0028
        },
        {
          "path": "navigation.attitude.roll",
          "value": -0.188
        },
        {
          "path": "navigation.speedThroughWater",
          "value": 3.23
        },
        {
          "path": "navigation.magneticVariation",
          "value": 0.2368
        },
        {
          "path": "navigation.speedOverGround",
          "value": 4.598888888888889
        },
        {
          "path": "navigation.courseOverGroundTrue",
          "value": 3.5054
        },
        {
          "path": "navigation.gnss.antennaAltitude",
          "value": -1.6
        },
        {
          "path": "navigation.gnss.satellites",
          "value": 9.0
        },
        {
          "path": "navigation.gnss.horizontalDilution",
          "value": 1.07
        },
        {
          "path": "navigation.gnss.geoidalSeparation",
          "value": -30.3
        },
        {
          "path": "navigation.gnss.positionDilution",
          "value": 2.03
        },
        {
          "path": "navigation.gnss.satellitesInView.count",
          "value": 12.0
        },
        {
          "path": "navigation.gnss.differentialAge",
          "value": 0.0
        },
        {
          "path": "navigation.gnss.differentialReference",
          "value": 0.0
        },
        {
          "path": "navigation.trip.log",
          "value": 667187.0
        },
        {
          "path": "navigation.log",
          "value": 667187.0
        },
        {
          "path": "navigation.headingTrue",
          "value": 3.6995
        },
        {
          "path": "navigation.averageSpeedThroughWater",
          "value": 3.51
        },
        {
          "path": "navigation.averageSpeedOverGround",
          "value": 4.48
        },
        {
          "path": "navigation.courseRhumbline.nextPoint.position",
          "value": {
            "longitude": -123.13381666666666,
            "latitude": 37.781933333333335
          }
        },
        {
          "path": "navigation.courseRhumbline.nextPoint.bearingTrue",
          "value": 3.763331293887013
        },
        {
          "path": "navigation.courseRhumbline.nextPoint.velocityMadeGood",
          "value": 4.601706721321259
        },
        {
          "path": "navigation.courseRhumbline.nextPoint.distance",
          "value": 11593.52000978493
        },
        {
          "path": "navigation.courseRhumbline.nextPoint.arrivalCircle",
          "value": 0.0
        },
        {
          "path": "navigation.courseRhumbline.crossTrackError",
          "value": 394.4760003329377
        },
        {
          "path": "navigation.courseRhumbline.previousPoint.position",
          "value": {
            "latitude": 37.98581,
            "longitude": -122.95769516666667
          }
        },
        {
          "path": "navigation.courseRhumbline.bearingTrackTrue",
          "value": 3.7973826676011977
        },
        {
          "path": "navigation.courseRhumbline.bearingOriginToDestinationTrue",
          "value": 3.7973826676011977
        },
        {
          "path": "navigation.courseRhumbline.bearingToDestinationTrue",
          "value": 3.763331293887013
        },
        {
          "path": "navigation.courseGreatCircle.nextPoint.position",
          "value": {
            "longitude": -123.13381666666666,
            "latitude": 37.781933333333335
          }
        },
        {
          "path": "navigation.courseGreatCircle.nextPoint.arrivalCircle",
          "value": 0.0
        },
        {
          "path": "navigation.courseGreatCircle.previousPoint.position",
          "value": {
            "latitude": 37.98581,
            "longitude": -122.95769516666667
          }
        },
        {
          "path": "navigation.course.calcValues.bearingTrackTrue",
          "value": 3.7409502641402095
        },
        {
          "path": "navigation.course.calcValues.bearingTrackMagnetic",
          "value": 3.9777502641402096
        },
        {
          "path": "navigation.course.calcValues.crossTrackError",
          "value": -275.8399969220645
        },
        {
          "path": "navigation.course.calcValues.previousPoint.distance",
          "value": 15841.839559833052
        },
        {
          "path": "navigation.course.calcValues.distance",
          "value": 11601.751649544054
        },
        {
          "path": "navigation.course.calcValues.bearingTrue",
          "value": 3.7636640251022433
        },
        {
          "path": "navigation.course.calcValues.bearingMagnetic",
          "value": 4.000464025102243
        },
        {
          "path": "navigation.course.calcValues.velocityMadeGood",
          "value": 4.530012738053524
        },
        {
          "path": "navigation.course.calcValues.timeToGo",
          "value": 2561.085
        },
        {
          "path": "navigation.anchor.position",
          "value": {
            "latitude": 38.01821902699977,
            "longitude": -122.97055041873854
          }
        },
        {
          "path": "navigation.anchor.distanceFromBow",
          "value": 18494.7
        },
        {
          "path": "navigation.anchor.bearingTrue",
          "value": 0.4225748779251409
        },
        {
          "path": "navigation.anchor.currentRadius",
          "value": 18486.8
        },
        {
          "path": "navigation.anchor.fudgeFactor",
          "value": 0.0
        },
        {
          "path": "navigation.anchor.apparentBearing",
          "value": 3.004260185104727
        },
        {
          "path": "navigation.anchor.maxRadius",
          "value": 45.0
        },
        {
          "path": "propulsion.port.revolutions",
          "value": 0.0
        },
        {
          "path": "propulsion.port.drive.trimState",
          "value": -1.0
        },
        {
          "path": "electrical.batteries.house.capacity.dischargeSinceFull",
          "value": -447480.0
        },
        {
          "path": "electrical.batteries.house.capacity.stateOfCharge",
          "value": 0.642
        },
        {
          "path": "electrical.batteries.house.capacity.timeRemaining",
          "value": 322680.0
        },
        {
          "path": "electrical.batteries.house.current",
          "value": 5.991
        },
        {
          "path": "electrical.batteries.house.power",
          "value": 76.20551999999999
        },
        {
          "path": "electrical.batteries.house.voltage",
          "value": 12.72
        },
        {
          "path": "tanks.fuel.0.currentVolume",
          "value": 0.1208
        },
        {
          "path": "tanks.fuel.0.currentLevel",
          "value": 0.8
        },
        {
          "path": "tanks.fuel.0.capacity",
          "value": 0.151
        },
        {
          "path": "tanks.fuel.reserve.temperature",
          "value": 286.15
        },
        {
          "path": "tanks.fuel.reserve.capacity",
          "value": 0.11356229999999999
        },
        {
          "path": "tanks.fuel.reserve.currentVolume",
          "value": 0.08513045700339107
        },
        {
          "path": "tanks.fuel.reserve.currentLevel",
          "value": 0.7496366047833751
        },
        {
          "path": "tanks.freshWater.0.currentVolume",
          "value": 0.2332
        },
        {
          "path": "tanks.freshWater.0.currentLevel",
          "value": 0.8799999999999999
        },
        {
          "path": "tanks.freshWater.0.capacity",
          "value": 0.265
        },
        {
          "path": "tanks.freshWater.1.currentVolume",
          "value": 0.0
        },
        {
          "path": "tanks.freshWater.1.currentLevel",
          "value": 0.0
        },
        {
          "path": "tanks.freshWater.1.capacity",
          "value": 0.265
        },
        {
          "path": "tanks.liveWell.0.currentLevel",
          "value": 0.06666666666666657
        },
        {
          "path": "tanks.liveWell.0.capacity",
          "value": 214748.36469999998
        },
        {
          "path": "tanks.propane.b.temperature",
          "value": 283.15
        },
        {
          "path": "tanks.propane.b.currentLevel",
          "value": 0.5330212634782611
        },
        {
          "path": "tanks.propane.a.temperature",
          "value": 287.15
        },
        {
          "path": "tanks.propane.a.currentLevel",
          "value": 0.387464795652174
        },
        {
          "path": "tanks.blackwater.stern.temperature",
          "value": 286.15
        },
        {
          "path": "tanks.blackwater.stern.currentLevel",
          "value": 0.0
        }
      ]
    }
  ]
}